cmake_presets_exploder/__init__.py
cmake_presets_exploder/__main__.py
cmake_presets_exploder/cli.py
cmake_presets_exploder/exploder.py
cmake_presets_exploder/py.typed
cmake_presets_exploder-0.3.3.dist-info/METADATA
cmake_presets_exploder-0.3.3.dist-info/WHEEL
cmake_presets_exploder-0.3.3.dist-info/entry_points.txt
cmake_presets_exploder-0.3.3.dist-info/licenses/LICENSE
cmake_presets_exploder-0.3.3.dist-info/RECORD
