Metadata-Version: 2.4
Name: cmake-presets-exploder
Version: 0.3.3
Summary: Automatically generate combinations of different CMake Presets options
Project-URL: Homepage, https://github.com/harrymander/cmake-presets-exploder
Project-URL: Repository, https://github.com/harrymander/cmake-presets-exploder
Author-email: Harry Mander <harrymander96@gmail.com>
License-Expression: MIT
License-File: LICENSE
Classifier: Development Status :: 4 - Beta
Classifier: Intended Audience :: Developers
Classifier: License :: OSI Approved :: MIT License
Classifier: Programming Language :: Python
Classifier: Programming Language :: Python :: 3
Classifier: Programming Language :: Python :: 3 :: Only
Classifier: Programming Language :: Python :: 3.9
Classifier: Programming Language :: Python :: 3.10
Classifier: Programming Language :: Python :: 3.11
Classifier: Programming Language :: Python :: 3.12
Classifier: Programming Language :: Python :: 3.13
Classifier: Programming Language :: Python :: Implementation :: CPython
Classifier: Programming Language :: Python :: Implementation :: PyPy
Classifier: Topic :: Software Development :: Build Tools
Classifier: Topic :: Software Development :: Code Generators
Classifier: Topic :: Software Development :: Libraries :: Python Modules
Classifier: Typing :: Typed
Requires-Python: >=3.9
Requires-Dist: click>=8.1.8
Requires-Dist: pydantic>=2.10.6
Provides-Extra: jinja2
Requires-Dist: jinja2>=3.1.5; extra == 'jinja2'
Provides-Extra: toml
Requires-Dist: tomli>=2.2.1; (python_full_version < '3.11') and extra == 'toml'
Provides-Extra: yaml
Requires-Dist: pyyaml>=6.0.2; extra == 'yaml'
